isylove/__init__.py
isylove/abc.py
isylove-0.1.2.dist-info/METADATA
isylove-0.1.2.dist-info/WHEEL
isylove-0.1.2.dist-info/RECORD
